pythonic_fp/containers/__init__.py
pythonic_fp/containers/__init__.pyi
pythonic_fp/containers/functional_tuple.py
pythonic_fp/containers/functional_tuple.pyi
pythonic_fp/containers/immutable_list.py
pythonic_fp/containers/immutable_list.pyi
pythonic_fp/containers/py.typed
pythonic_fp_containers-4.0.1.dist-info/licenses/LICENSE
pythonic_fp_containers-4.0.1.dist-info/WHEEL
pythonic_fp_containers-4.0.1.dist-info/METADATA
pythonic_fp_containers-4.0.1.dist-info/RECORD
